MANIFEST.in
README.md
setup.py
cliPublish/__init__.py
cliPublish/cliPublish.py
cliPublish/remotes.conf.example
cliPublish.egg-info/PKG-INFO
cliPublish.egg-info/SOURCES.txt
cliPublish.egg-info/dependency_links.txt
cliPublish.egg-info/entry_points.txt
cliPublish.egg-info/top_level.txt