Metadata-Version: 1.1
Name: cliPublish
Version: 0.2.0
Summary: Convenient commandline utility to publish files on a webserver using rsync
Home-page: https://github.com/mheistermann/cliPublish
Author: Martin Heistermann
Author-email: sieve-git-pushdeploy@mheistermann.de
License: GPLv3+
Keywords: rsync upload cli
Platform: UNKNOWN
Classifier: Development Status :: 4 - Beta
Classifier: License :: OSI Approved :: GNU General Public License v3 or later (GPLv3+)
Classifier: Programming Language :: Python :: 3 :: Only
